{
  "subject": "botany",
  "chapterTitle": "7. Cell - The unit of Life",
  "chapterNumber": 7,
  "titleSlug": "7-cell-the-unit-of-life",
  "pages": [
    {
      "page": 1,
      "url": "https://cdn.jsdelivr.net/gh/Habibullah-sekh/canvas-3@main/ncert/svgs/1762956163527_9pdrfq.svg",
      "fileName": "1762956163527_9pdrfq.svg"
    },
    {
      "page": 2,
      "url": "https://cdn.jsdelivr.net/gh/Habibullah-sekh/canvas-3@main/ncert/svgs/1762956165916_t39lkd.svg",
      "fileName": "1762956165916_t39lkd.svg"
    },
    {
      "page": 3,
      "url": "https://cdn.jsdelivr.net/gh/Habibullah-sekh/canvas-3@main/ncert/svgs/1762956168227_ji433m.svg",
      "fileName": "1762956168227_ji433m.svg"
    },
    {
      "page": 4,
      "url": "https://cdn.jsdelivr.net/gh/Habibullah-sekh/canvas-3@main/ncert/svgs/1762956170084_ieo3eb.svg",
      "fileName": "1762956170084_ieo3eb.svg"
    },
    {
      "page": 5,
      "url": "https://cdn.jsdelivr.net/gh/Habibullah-sekh/canvas-3@main/ncert/svgs/1762956171208_a8z4lc.svg",
      "fileName": "1762956171208_a8z4lc.svg"
    },
    {
      "page": 6,
      "url": "https://cdn.jsdelivr.net/gh/Habibullah-sekh/canvas-3@main/ncert/svgs/1762956173460_t88aog.svg",
      "fileName": "1762956173460_t88aog.svg"
    },
    {
      "page": 7,
      "url": "https://cdn.jsdelivr.net/gh/Habibullah-sekh/canvas-3@main/ncert/svgs/1762956175173_encxuc.svg",
      "fileName": "1762956175173_encxuc.svg"
    },
    {
      "page": 8,
      "url": "https://cdn.jsdelivr.net/gh/Habibullah-sekh/canvas-3@main/ncert/svgs/1762956176430_9z10dl.svg",
      "fileName": "1762956176430_9z10dl.svg"
    },
    {
      "page": 9,
      "url": "https://cdn.jsdelivr.net/gh/Habibullah-sekh/canvas-3@main/ncert/svgs/1762956185957_2wpgp6.svg",
      "fileName": "1762956185957_2wpgp6.svg"
    },
    {
      "page": 10,
      "url": "https://cdn.jsdelivr.net/gh/Habibullah-sekh/canvas-3@main/ncert/svgs/1762956188200_17i2nq.svg",
      "fileName": "1762956188200_17i2nq.svg"
    },
    {
      "page": 11,
      "url": "https://cdn.jsdelivr.net/gh/Habibullah-sekh/canvas-3@main/ncert/svgs/1762956189571_zjdq2z.svg",
      "fileName": "1762956189571_zjdq2z.svg"
    },
    {
      "page": 12,
      "url": "https://cdn.jsdelivr.net/gh/Habibullah-sekh/canvas-3@main/ncert/svgs/1762956193873_a9i3uz.svg",
      "fileName": "1762956193873_a9i3uz.svg"
    },
    {
      "page": 13,
      "url": "https://cdn.jsdelivr.net/gh/Habibullah-sekh/canvas-3@main/ncert/svgs/1762956195363_crslvq.svg",
      "fileName": "1762956195363_crslvq.svg"
    },
    {
      "page": 14,
      "url": "https://cdn.jsdelivr.net/gh/Habibullah-sekh/canvas-3@main/ncert/svgs/1762956197657_926lnl.svg",
      "fileName": "1762956197657_926lnl.svg"
    },
    {
      "page": 15,
      "url": "https://cdn.jsdelivr.net/gh/Habibullah-sekh/canvas-3@main/ncert/svgs/1762956201709_cy8id6.svg",
      "fileName": "1762956201709_cy8id6.svg"
    },
    {
      "page": 16,
      "url": "https://cdn.jsdelivr.net/gh/Habibullah-sekh/canvas-3@main/ncert/svgs/1762956203309_zovepl.svg",
      "fileName": "1762956203309_zovepl.svg"
    },
    {
      "page": 17,
      "url": "https://cdn.jsdelivr.net/gh/Habibullah-sekh/canvas-3@main/ncert/svgs/1762956205475_hz1jz3.svg",
      "fileName": "1762956205475_hz1jz3.svg"
    },
    {
      "page": 18,
      "url": "https://cdn.jsdelivr.net/gh/Habibullah-sekh/canvas-3@main/ncert/svgs/1762956208395_5ezcc7.svg",
      "fileName": "1762956208395_5ezcc7.svg"
    },
    {
      "page": 19,
      "url": "https://cdn.jsdelivr.net/gh/Habibullah-sekh/canvas-3@main/ncert/svgs/1762956209760_7anvmi.svg",
      "fileName": "1762956209760_7anvmi.svg"
    }
  ]
}